bootstrap.wpr
setup.cfg
setup.py
docs/index.txt
docs/license.txt
tg_bootstrap/__init__.py
tg_bootstrap/bootstrap.py
tg_bootstrap/finddata.py
tg_bootstrap.egg-info/PKG-INFO
tg_bootstrap.egg-info/SOURCES.txt
tg_bootstrap.egg-info/dependency_links.txt
tg_bootstrap.egg-info/requires.txt
tg_bootstrap.egg-info/top_level.txt
tg_bootstrap.egg-info/zip-safe
