Metadata-Version: 1.0
Name: tg-bootstrap
Version: 0.4.0
Summary: Bootstrap a TurboGears app in a VirtualEnv
Home-page: http://pypi.python.org/pypi/tg_bootstrap
Author: Arlo Belshee
Author-email: a+tg_bootstrap@arlim.org
License: MIT
Keywords: setuptools deployment installation virtualenv turbogears
Platform: UNKNOWN
Classifier: Development Status :: 4 - Beta
Classifier: Intended Audience :: Developers
Classifier: License :: OSI Approved :: MIT License
